simstack/__init__.py
simstack/_version.py
simstack/core/__init__.py
simstack/core/artifacts.py
simstack/core/asnyc_helper.py
simstack/core/config_file.py
simstack/core/context.py
simstack/core/data.py
simstack/core/definitions.py
simstack/core/engine.py
simstack/core/find_simstack_modules.py
simstack/core/hash.py
simstack/core/model_table.py
simstack/core/node.py
simstack/core/node_runner.py
simstack/core/node_table.py
simstack/core/recompute_artifacts.py
simstack/core/reset_db.py
simstack/core/resources.py
simstack/core/run_node.py
simstack/core/runner.py
simstack/core/simstack_result.py
simstack/core/submit_node.py
simstack/core/task_id.py
simstack/data/__init__.py
simstack/methods/__init__.py
simstack/methods/get_file.py
simstack/methods/multiple_executor.py
simstack/models/__init__.py
simstack/models/array_list.py
simstack/models/array_storage.py
simstack/models/artifact_models.py
simstack/models/base_types.py
simstack/models/charts_artifact.py
simstack/models/dataset.py
simstack/models/dataset_metadata.py
simstack/models/file_instance.py
simstack/models/file_list.py
simstack/models/files.py
simstack/models/log_entry_model.py
simstack/models/models.py
simstack/models/node_registry.py
simstack/models/pandas_model.py
simstack/models/parameters.py
simstack/models/pickle_models.py
simstack/models/runner_model.py
simstack/models/simple_table.py
simstack/models/simstack_model.py
simstack/models/slurm_info.py
simstack/models/table_artifact.py
simstack/util/__init__.py
simstack/util/async_zip_utils.py
simstack/util/cleaned_json_schema.py
simstack/util/config_reader.py
simstack/util/custom_model_dump.py
simstack/util/db.py
simstack/util/db_logger.py
simstack/util/default_from_dict.py
simstack/util/directory_iterator.py
simstack/util/file_hashing.py
simstack/util/files.py
simstack/util/find_python_files.py
simstack/util/generate_ui_schema.py
simstack/util/geometry_utils.py
simstack/util/get_module_path.py
simstack/util/git_pull.py
simstack/util/git_repository_status.py
simstack-0.2.0.dist-info/licenses/LICENSE
simstack-0.2.0.dist-info/METADATA
simstack-0.2.0.dist-info/WHEEL
simstack-0.2.0.dist-info/entry_points.txt
simstack-0.2.0.dist-info/top_level.txt
simstack-0.2.0.dist-info/RECORD
