Metadata-Version: 2.4
Name: simstack
Version: 0.2.0
Summary: A python based workflow engineering platform with a react-js UI
Author-email: Wolfgang Wenzel <wolfgang.wenzel@kit.edu>, Timo Strunk <timo.strunk@nanomatch.de>
License: MIT
Project-URL: Homepage, https://gitlab.kit.edu/kit/ag_wenzel/simstack-model/
Requires-Python: >=3.12
License-File: LICENSE
Requires-Dist: odmantic<2,>=1.0.2
Requires-Dist: cloudpickle<4,>=3.1.1
Requires-Dist: coolname<3,>=2.2.0
Requires-Dist: nest-asyncio<2,>=1.6.0
Requires-Dist: numpy>=2.3.0
Requires-Dist: pandas>=2.3.3
Dynamic: license-file
